README.md
setup.py
fslomka_hello_world.egg-info/PKG-INFO
fslomka_hello_world.egg-info/SOURCES.txt
fslomka_hello_world.egg-info/dependency_links.txt
fslomka_hello_world.egg-info/top_level.txt
sample_package/__init__.py
sample_package/sample.py
sample_package/setup.py